plin/__init__.py
plin/device.py
plin/enums.py
plin/structs.py
plin_linux-0.0.3.dist-info/LICENSE
plin_linux-0.0.3.dist-info/METADATA
plin_linux-0.0.3.dist-info/WHEEL
plin_linux-0.0.3.dist-info/top_level.txt
plin_linux-0.0.3.dist-info/RECORD
