Metadata-Version: 2.1
Name: plin-linux
Version: 0.0.3
Summary: The python-plin package is a Python wrapper for the chardev API provided by the PEAK LIN Linux Beta.
Author-email: William Zhang <williamzhang@rivian.com>
Project-URL: Homepage, https://github.com/rivian/python-plin
Project-URL: Bug Tracker, https://github.com/rivian/python-plin/issues
Classifier: Programming Language :: Python :: 3
Classifier: License :: OSI Approved :: Apache Software License
Classifier: Operating System :: POSIX :: Linux
Requires-Python: >=3.7
License-File: LICENSE
Requires-Dist: ioctl-opt
